pkg/__init__.py
pkg/__main__.py
pkg/config.txt
chonsoft_utils-1.0.0.dist-info/LICENSE
chonsoft_utils-1.0.0.dist-info/METADATA
chonsoft_utils-1.0.0.dist-info/WHEEL
chonsoft_utils-1.0.0.dist-info/entry_points.txt
chonsoft_utils-1.0.0.dist-info/top_level.txt
chonsoft_utils-1.0.0.dist-info/RECORD
