Metadata-Version: 2.1
Name: chonsoft-utils
Version: 1.0.0
Summary: chonsoft utils package
Home-page: UNKNOWN
Author: chonsoft
Author-email: chonsoft@hotmail.com
License: MIT
Platform: UNKNOWN
Classifier: License :: OSI Approved :: MIT License
Classifier: Programming Language :: Python :: 3
Classifier: Programming Language :: Python :: 3.7
